mijoon_cmd/__init__.py
mijoon_cmd/cmd.py
mijoon_cmd-0.3.0.dist-info/METADATA
mijoon_cmd-0.3.0.dist-info/WHEEL
mijoon_cmd-0.3.0.dist-info/entry_points.txt
mijoon_cmd-0.3.0.dist-info/top_level.txt
mijoon_cmd-0.3.0.dist-info/RECORD
