Metadata-Version: 2.1
Name: mijoon_cmd
Version: 0.3.0
Summary: Default template for PDM package
Author-email: Kimwonjoon <kimpass189@gmail.com>
License: MIT
Project-URL: Homepage, https://github.com/Kimwonjoon/mijoon_cmd
Project-URL: Issues, https://github.com/Kimwonjoon/mijoon_cmd/issues
Requires-Python: >=3.9
Requires-Dist: team-divide >=0.1.3
Requires-Dist: team-mul >=0.1.1
Requires-Dist: team-plus >=0.4.0
